ClusterAPIServer-0.1.dist-info/METADATA
ClusterAPIServer-0.1.dist-info/RECORD
ClusterAPIServer-0.1.dist-info/WHEEL
ClusterAPIServer-0.1.dist-info/top_level.txt
app/__init__.py
app/config.py
app/auth/__init__.py
app/auth/helper.py
app/auth/views.py
app/cluster/__init__.py
app/cluster/helper.py
app/cluster/views.py
app/common/__init__.py
app/common/helper.py
app/corosync/__init__.py
app/corosync/views.py
app/node/__init__.py
app/node/helper.py
app/node/views.py
app/resource/__init__.py
app/resource/helper.py
app/resource/views.py
