Metadata-Version: 2.1
Name: ClusterAPIServer
Version: 0.1
Summary: UNKNOWN
Home-page: UNKNOWN
Author: Xin Liang
Author-email: XLiang@suse.com
License: UNKNOWN
Platform: UNKNOWN
Requires-Dist: Flask
Requires-Dist: xmltodict
Requires-Dist: PyJWT
Requires-Dist: python-pam
